cdk_databrew_cicd/__init__.py
cdk_databrew_cicd/py.typed
cdk_databrew_cicd/_jsii/__init__.py
cdk_databrew_cicd/_jsii/cdk-databrew-cicd@2.0.636.jsii.tgz
cdk_databrew_cicd-2.0.636.dist-info/LICENSE
cdk_databrew_cicd-2.0.636.dist-info/METADATA
cdk_databrew_cicd-2.0.636.dist-info/WHEEL
cdk_databrew_cicd-2.0.636.dist-info/top_level.txt
cdk_databrew_cicd-2.0.636.dist-info/RECORD
